mostats/__init__.py
mostats/getCluster.py
mostats-1.0.20.dist-info/LICENSE
mostats-1.0.20.dist-info/METADATA
mostats-1.0.20.dist-info/WHEEL
mostats-1.0.20.dist-info/entry_points.txt
mostats-1.0.20.dist-info/top_level.txt
mostats-1.0.20.dist-info/RECORD
