Metadata-Version: 2.1
Name: mostats
Version: 1.0.20
Summary: Get the MongoDB database statistic to a local excel file
Home-page: https://github.com/pix3lize/mostats
Author: Hendri Tjipto
Classifier: Intended Audience :: Developers
Classifier: Programming Language :: Python :: 3
Classifier: Operating System :: Unix
Classifier: Operating System :: MacOS :: MacOS X
Classifier: Operating System :: Microsoft :: Windows
Requires-Python: >=3.10.7
License-File: LICENSE
Requires-Dist: pymongo >=4.4.1
Requires-Dist: pandas >=2.0.3
Requires-Dist: argparse
Requires-Dist: openpyxl >=3.1.2
Requires-Dist: xlsxwriter >=3.1.2
Requires-Dist: numpy >=1.25.1
